gpg_qr/__init__.py
gpg_qr/main.py
gpg_qrcode-0.1.3.dist-info/LICENSE
gpg_qrcode-0.1.3.dist-info/METADATA
gpg_qrcode-0.1.3.dist-info/WHEEL
gpg_qrcode-0.1.3.dist-info/entry_points.txt
gpg_qrcode-0.1.3.dist-info/top_level.txt
gpg_qrcode-0.1.3.dist-info/RECORD
