Metadata-Version: 2.2
Name: gpg-qrcode
Version: 0.1.3
Summary: A tool for generating qr-codes from gpg ascii keys and revoke certificates
Home-page: https://github.com/ubuntupunk/gpg-qrcode
Author: David Robert Lewis
Author-email: ubuntupunk@gmail.com
Keywords: revoke,gpg,qrcode
Classifier: Programming Language :: Python :: 3
Classifier: Operating System :: OS Independent
Requires-Python: >=3.6
License-File: LICENSE
Requires-Dist: qrcode
Requires-Dist: requests
Requires-Dist: pillow
Dynamic: author
Dynamic: author-email
Dynamic: classifier
Dynamic: description
Dynamic: description-content-type
Dynamic: home-page
Dynamic: keywords
Dynamic: requires-dist
Dynamic: requires-python
Dynamic: summary
